kiutils/__init__.py
kiutils/board.py
kiutils/dru.py
kiutils/footprint.py
kiutils/libraries.py
kiutils/schematic.py
kiutils/symbol.py
kiutils/wks.py
kiutils/items/brditems.py
kiutils/items/common.py
kiutils/items/dimensions.py
kiutils/items/fpitems.py
kiutils/items/gritems.py
kiutils/items/schitems.py
kiutils/items/syitems.py
kiutils/items/zones.py
kiutils/misc/config.py
kiutils/utils/sexpr.py
kiutils/utils/strings.py
kiutils-1.4.7.dist-info/LICENSE
kiutils-1.4.7.dist-info/METADATA
kiutils-1.4.7.dist-info/WHEEL
kiutils-1.4.7.dist-info/top_level.txt
kiutils-1.4.7.dist-info/RECORD
