Metadata-Version: 2.1
Name: kiutils
Version: 1.4.7
Summary: Simple and SCM-friendly KiCad file parser for KiCad 6.0 and up
Home-page: https://github.com/mvnmgrx/kiutils
Author: Marvin Mager
Author-email: 99667992+mvnmgrx@users.noreply.github.com
Project-URL: Bug Tracker, https://github.com/mvnmgrx/kiutils/issues
Classifier: Programming Language :: Python :: 3.7
Classifier: Programming Language :: Python :: 3.8
Classifier: Programming Language :: Python :: 3.9
Classifier: Programming Language :: Python :: 3.10
Classifier: Programming Language :: Python :: 3.11
Classifier: License :: OSI Approved :: GNU General Public License v3 (GPLv3)
Classifier: Operating System :: OS Independent
Classifier: Development Status :: 5 - Production/Stable
Classifier: Natural Language :: English
Classifier: Topic :: Scientific/Engineering :: Electronic Design Automation (EDA)
Requires-Python: >=3.7
License-File: LICENSE
